{
  "8868": [
    "P1",
    "E16",
    "M3",
    "E6",
    "M1",
    "log_ret_lag_38",
    "V11",
    "log_ret_lag_41",
    "E4",
    "log_ret_cum_31d",
    "log_ret_lag_31",
    "S7",
    "log_ret_cum_58d",
    "log_ret_cum_4d",
    "log_ret_cum_38d",
    "E8",
    "log_ret_cum_37d",
    "log_ret_lag_55",
    "P12",
    "S8",
    "V9",
    "M11",
    "D4",
    "M7",
    "log_ret_lag_29",
    "P2",
    "E7",
    "I1",
    "log_ret_cum_3d",
    "log_ret_cum_40d"
  ],
  "8888": [
    "log_ret_cum_24d",
    "I1",
    "I2",
    "I6",
    "P2",
    "log_ret_cum_7d",
    "M14",
    "P8",
    "log_ret_lag_17",
    "P13",
    "V5",
    "M11",
    "log_ret_cum_12d",
    "D9",
    "M1",
    "log_ret_cum_34d",
    "S1",
    "I7",
    "V13",
    "log_ret_cum_54d",
    "E16",
    "S7",
    "log_ret_cum_25d",
    "E4",
    "D5",
    "M16",
    "log_ret_cum_27d",
    "P3",
    "log_ret_cum_42d",
    "E17"
  ],
  "8908": [
    "M16",
    "S2",
    "log_ret_cum_15d",
    "log_ret_cum_24d",
    "log_ret_cum_44d",
    "log_ret_cum_41d",
    "M3",
    "M18",
    "log_ret_cum_48d",
    "P13",
    "log_ret_cum_37d",
    "log_ret_cum_29d",
    "M5",
    "log_ret_cum_27d",
    "M17",
    "log_ret_cum_22d",
    "I3",
    "log_ret_cum_26d",
    "log_ret_cum_16d",
    "E6",
    "I6",
    "log_ret_cum_21d",
    "I4",
    "log_ret_cum_20d",
    "log_ret_cum_56d",
    "M7",
    "log_ret_cum_28d",
    "I5",
    "log_ret_cum_18d",
    "P10"
  ],
  "8928": [
    "log_ret_cum_25d",
    "P2",
    "log_ret_cum_34d",
    "log_ret_cum_46d",
    "log_ret_cum_26d",
    "I9",
    "I5",
    "V13",
    "log_ret_cum_40d",
    "log_ret_cum_8d",
    "log_ret_cum_35d",
    "M11",
    "log_ret_cum_43d",
    "M10",
    "log_ret_cum_28d",
    "M9",
    "log_ret_cum_42d",
    "log_ret_cum_38d",
    "M3",
    "M5",
    "log_ret_lag_53",
    "I4",
    "log_ret_cum_32d",
    "log_ret_cum_31d",
    "log_ret_cum_23d",
    "log_ret_cum_16d",
    "log_ret_cum_33d",
    "log_ret_cum_53d",
    "log_ret_lag_51",
    "log_ret_lag_4"
  ],
  "8948": [
    "S3",
    "log_ret_cum_53d",
    "M1",
    "log_ret_cum_51d",
    "E18",
    "E20",
    "E19",
    "log_ret_cum_45d",
    "I5",
    "P4",
    "E9",
    "P10",
    "log_ret_cum_43d",
    "log_ret_cum_31d",
    "log_ret_cum_42d",
    "E5",
    "E3",
    "E17",
    "M7",
    "log_ret_cum_59d",
    "log_ret_lag_22",
    "E16",
    "V7",
    "log_ret_cum_3d",
    "log_ret_cum_38d",
    "log_ret_cum_47d",
    "log_ret_cum_19d",
    "log_ret_cum_17d",
    "E13",
    "P2"
  ],
  "8968": [
    "log_ret_cum_28d",
    "log_ret_cum_30d",
    "E6",
    "P2",
    "E2",
    "E7",
    "log_ret_cum_22d",
    "S3",
    "log_ret_cum_40d",
    "E16",
    "P10",
    "log_ret_lag_53",
    "log_ret_cum_58d",
    "E5",
    "M1",
    "log_ret_lag_56",
    "log_ret_lag_21",
    "log_ret_cum_35d",
    "log_ret_lag_41",
    "log_ret_cum_36d",
    "M8",
    "log_ret_lag_28",
    "E1",
    "log_ret_lag_24",
    "log_ret_cum_49d",
    "I4",
    "E13",
    "log_ret_cum_4d",
    "log_ret_cum_51d",
    "P1"
  ],
  "8988": [
    "log_ret_cum_21d",
    "E13",
    "M10",
    "E12",
    "P9",
    "V1",
    "V11",
    "P1",
    "I4",
    "E7",
    "log_ret_cum_40d",
    "log_ret_cum_30d",
    "E15",
    "P2",
    "M5",
    "log_ret_cum_37d",
    "M3",
    "M17",
    "M13",
    "E16",
    "M9",
    "log_ret_cum_59d",
    "E2",
    "log_ret_lag_27",
    "log_ret_lag_15",
    "M16",
    "E9",
    "S3",
    "E6",
    "log_ret_cum_60d"
  ],
  "9008": [
    "log_ret_cum_30d",
    "E7",
    "E6",
    "S4",
    "log_ret_cum_42d",
    "M15",
    "S1",
    "I9",
    "D9",
    "E13",
    "log_ret_cum_7d",
    "E5",
    "D5",
    "S3",
    "E8",
    "log_ret_lag_60",
    "log_ret_cum_26d",
    "M1",
    "log_ret_cum_46d",
    "E16",
    "V13",
    "E1",
    "log_ret_cum_33d",
    "I6",
    "M12",
    "E11",
    "I1",
    "log_ret_lag_58",
    "log_ret_cum_22d",
    "log_ret_lag_24"
  ],
  "9028": [
    "M10",
    "log_ret_cum_22d",
    "I8",
    "log_ret_cum_30d",
    "log_ret_cum_49d",
    "E7",
    "log_ret_cum_42d",
    "V9",
    "log_ret_cum_40d",
    "I7",
    "log_ret_cum_58d",
    "log_ret_cum_53d",
    "log_ret_cum_59d",
    "S2",
    "log_ret_cum_35d",
    "V3",
    "log_ret_cum_25d",
    "log_ret_cum_39d",
    "log_ret_cum_27d",
    "log_ret_cum_55d",
    "log_ret_cum_28d",
    "log_ret_cum_54d",
    "M5",
    "log_ret_cum_47d",
    "P10",
    "log_ret_cum_26d",
    "M7",
    "log_ret_lag_19",
    "V13",
    "log_ret_cum_51d"
  ]
}