{
  "8868": [
    "log_ret_cum_12d",
    "log_ret_cum_11d",
    "log_ret_cum_15d",
    "log_ret_cum_16d",
    "log_ret_cum_34d",
    "log_ret_cum_5d",
    "log_ret_cum_35d",
    "log_ret_cum_47d",
    "log_ret_cum_13d",
    "log_ret_lag_8",
    "log_ret_cum_18d",
    "log_ret_cum_17d",
    "log_ret_cum_33d",
    "log_ret_lag_11",
    "log_ret_cum_22d",
    "log_ret_cum_57d",
    "log_ret_cum_40d",
    "log_ret_lag_10",
    "log_ret_cum_45d",
    "log_ret_cum_56d",
    "log_ret_cum_21d",
    "log_ret_cum_14d",
    "log_ret_cum_39d",
    "log_ret_cum_20d",
    "log_ret_lag_9",
    "log_ret_cum_26d",
    "log_ret_lag_7",
    "log_ret_lag_6",
    "log_ret_cum_54d",
    "log_ret_cum_46d"
  ],
  "8888": [
    "log_ret_cum_6d",
    "log_ret_cum_2d",
    "log_ret_cum_7d",
    "log_ret_cum_58d",
    "log_ret_cum_4d",
    "log_ret_cum_5d",
    "log_ret_cum_60d",
    "log_ret_cum_47d",
    "log_ret_cum_9d",
    "log_ret_cum_56d",
    "log_ret_cum_59d",
    "log_ret_cum_14d",
    "log_ret_cum_51d",
    "log_ret_lag_3",
    "log_ret_cum_15d",
    "log_ret_cum_8d",
    "log_ret_lag_56",
    "log_ret_lag_54",
    "log_ret_lag_55",
    "log_ret_lag_53",
    "log_ret_cum_49d",
    "log_ret_lag_4",
    "log_ret_lag_7",
    "log_ret_cum_52d",
    "log_ret_lag_52",
    "log_ret_lag_57",
    "log_ret_cum_11d",
    "log_ret_cum_18d",
    "log_ret_cum_35d",
    "log_ret_lag_58"
  ],
  "8908": [
    "log_ret_cum_4d",
    "log_ret_cum_6d",
    "log_ret_cum_8d",
    "log_ret_cum_12d",
    "log_ret_cum_56d",
    "log_ret_cum_5d",
    "log_ret_cum_14d",
    "log_ret_cum_22d",
    "log_ret_cum_59d",
    "log_ret_lag_3",
    "log_ret_cum_27d",
    "log_ret_lag_4",
    "log_ret_cum_34d",
    "log_ret_cum_49d",
    "log_ret_cum_18d",
    "log_ret_cum_33d",
    "log_ret_cum_15d",
    "log_ret_cum_52d",
    "log_ret_lag_5",
    "log_ret_lag_8",
    "log_ret_cum_9d",
    "log_ret_cum_2d",
    "log_ret_lag_32",
    "log_ret_cum_47d",
    "log_ret_cum_17d",
    "log_ret_lag_33",
    "log_ret_cum_36d",
    "log_ret_lag_7",
    "log_ret_cum_21d",
    "log_ret_cum_13d"
  ],
  "8928": [
    "log_ret_cum_8d",
    "log_ret_cum_6d",
    "log_ret_cum_16d",
    "log_ret_cum_15d",
    "log_ret_cum_20d",
    "log_ret_cum_55d",
    "log_ret_cum_21d",
    "log_ret_cum_14d",
    "log_ret_cum_4d",
    "log_ret_lag_18",
    "log_ret_cum_3d",
    "log_ret_cum_17d",
    "log_ret_lag_19",
    "log_ret_cum_9d",
    "log_ret_lag_7",
    "log_ret_cum_12d",
    "log_ret_lag_3",
    "log_ret_cum_22d",
    "log_ret_cum_7d",
    "log_ret_lag_20",
    "log_ret_lag_17",
    "log_ret_cum_44d",
    "log_ret_lag_2",
    "log_ret_cum_23d",
    "log_ret_cum_33d",
    "log_ret_lag_8",
    "log_ret_cum_53d",
    "log_ret_cum_41d",
    "log_ret_lag_21",
    "log_ret_cum_26d"
  ],
  "8948": [
    "log_ret_cum_6d",
    "log_ret_cum_8d",
    "log_ret_cum_15d",
    "log_ret_cum_12d",
    "log_ret_cum_16d",
    "log_ret_cum_7d",
    "log_ret_cum_14d",
    "log_ret_lag_7",
    "log_ret_lag_3",
    "log_ret_cum_3d",
    "log_ret_cum_20d",
    "log_ret_cum_4d",
    "log_ret_cum_9d",
    "log_ret_cum_55d",
    "log_ret_cum_18d",
    "log_ret_lag_18",
    "log_ret_cum_17d",
    "log_ret_lag_2",
    "log_ret_cum_54d",
    "log_ret_cum_56d",
    "log_ret_cum_53d",
    "log_ret_lag_49",
    "log_ret_lag_50",
    "log_ret_cum_46d",
    "log_ret_lag_48",
    "log_ret_lag_51",
    "log_ret_cum_13d",
    "log_ret_lag_52",
    "log_ret_lag_17",
    "log_ret_lag_53"
  ],
  "8968": [
    "log_ret_cum_7d",
    "log_ret_cum_9d",
    "log_ret_cum_6d",
    "log_ret_cum_3d",
    "log_ret_cum_8d",
    "log_ret_lag_2",
    "log_ret_lag_3",
    "log_ret_lag_7",
    "log_ret_cum_14d",
    "log_ret_cum_12d",
    "log_ret_cum_15d",
    "log_ret_lag_1",
    "log_ret_cum_17d",
    "log_ret_cum_44d",
    "log_ret_lag_49",
    "log_ret_cum_56d",
    "log_ret_cum_43d",
    "log_ret_lag_48",
    "log_ret_lag_51",
    "log_ret_cum_54d",
    "log_ret_lag_50",
    "log_ret_lag_52",
    "log_ret_cum_16d",
    "log_ret_cum_10d",
    "log_ret_lag_53",
    "log_ret_lag_47",
    "log_ret_lag_46",
    "log_ret_lag_54",
    "log_ret_cum_59d",
    "log_ret_cum_26d"
  ],
  "8988": [
    "log_ret_cum_8d",
    "log_ret_cum_14d",
    "log_ret_cum_19d",
    "log_ret_cum_15d",
    "log_ret_cum_6d",
    "log_ret_cum_20d",
    "log_ret_cum_21d",
    "log_ret_lag_18",
    "log_ret_cum_3d",
    "log_ret_cum_16d",
    "log_ret_cum_10d",
    "log_ret_lag_17",
    "log_ret_lag_19",
    "log_ret_cum_11d",
    "log_ret_cum_18d",
    "log_ret_cum_37d",
    "log_ret_lag_16",
    "log_ret_cum_45d",
    "log_ret_cum_22d",
    "log_ret_cum_17d",
    "log_ret_cum_57d",
    "log_ret_cum_55d",
    "log_ret_lag_48",
    "log_ret_lag_47",
    "log_ret_lag_49",
    "log_ret_cum_41d",
    "log_ret_lag_50",
    "log_ret_lag_7",
    "log_ret_lag_54",
    "log_ret_lag_53"
  ],
  "9008": [
    "log_ret_cum_6d",
    "log_ret_cum_14d",
    "log_ret_cum_8d",
    "log_ret_cum_18d",
    "log_ret_cum_3d",
    "log_ret_cum_20d",
    "log_ret_cum_15d",
    "log_ret_lag_17",
    "log_ret_lag_18",
    "log_ret_cum_28d",
    "log_ret_cum_4d",
    "log_ret_cum_27d",
    "log_ret_cum_19d",
    "log_ret_cum_21d",
    "log_ret_cum_29d",
    "log_ret_lag_16",
    "log_ret_cum_23d",
    "log_ret_lag_2",
    "log_ret_cum_16d",
    "log_ret_lag_19",
    "log_ret_cum_41d",
    "log_ret_lag_3",
    "log_ret_cum_35d",
    "log_ret_lag_5",
    "log_ret_lag_7",
    "log_ret_cum_10d",
    "log_ret_cum_34d",
    "log_ret_cum_7d",
    "log_ret_cum_59d",
    "log_ret_cum_40d"
  ],
  "9028": [
    "log_ret_cum_6d",
    "log_ret_cum_16d",
    "log_ret_cum_20d",
    "log_ret_cum_12d",
    "log_ret_cum_17d",
    "log_ret_cum_3d",
    "log_ret_cum_19d",
    "log_ret_cum_21d",
    "log_ret_lag_19",
    "log_ret_lag_18",
    "log_ret_cum_36d",
    "log_ret_cum_15d",
    "log_ret_cum_14d",
    "log_ret_cum_47d",
    "log_ret_cum_46d",
    "log_ret_lag_3",
    "log_ret_cum_55d",
    "log_ret_cum_35d",
    "log_ret_cum_4d",
    "log_ret_lag_20",
    "log_ret_cum_56d",
    "log_ret_lag_50",
    "log_ret_lag_51",
    "log_ret_lag_52",
    "log_ret_lag_53",
    "log_ret_cum_27d",
    "log_ret_lag_17",
    "log_ret_lag_49",
    "log_ret_cum_22d",
    "log_ret_cum_58d"
  ]
}